bigquery_operator/__init__.py
bigquery_operator/operator.py
bigquery_operator/operator_quick_setup.py
bigquery_operator-2.0.dist-info/LICENSE
bigquery_operator-2.0.dist-info/METADATA
bigquery_operator-2.0.dist-info/WHEEL
bigquery_operator-2.0.dist-info/top_level.txt
bigquery_operator-2.0.dist-info/RECORD
