Metadata-Version: 2.1
Name: bigquery-operator
Version: 2.0
Summary: Wrapper for usual operations on a fixed BigQuery dataset.
Home-page: UNKNOWN
Author: Augustin Barillec
Author-email: augustin.barillec@gmail.com
License: UNKNOWN
Project-URL: Documentation, https://bigquery-operator.readthedocs.io/en/latest/
Project-URL: Source, https://github.com/augustin-barillec/bigquery-operator
Platform: UNKNOWN
Classifier: Programming Language :: Python :: 3.6
Classifier: Programming Language :: Python :: 3.7
Classifier: Programming Language :: Python :: 3.8
Classifier: Programming Language :: Python :: 3.9
Classifier: Programming Language :: Python :: 3.10
Classifier: Programming Language :: Python :: 3.11
Classifier: License :: OSI Approved :: MIT License
Classifier: Operating System :: POSIX :: Linux
License-File: LICENSE
Requires-Dist: google-cloud-bigquery (==3.*)
